oarepo_oidc_einfra/__init__.py
oarepo_oidc_einfra/cli.py
oarepo_oidc_einfra/communities.py
oarepo_oidc_einfra/config.py
oarepo_oidc_einfra/encryption.py
oarepo_oidc_einfra/ext.py
oarepo_oidc_einfra/mutex.py
oarepo_oidc_einfra/proxies.py
oarepo_oidc_einfra/remote.py
oarepo_oidc_einfra/resources.py
oarepo_oidc_einfra/tasks.py
oarepo_oidc_einfra/perun/__init__.py
oarepo_oidc_einfra/perun/api.py
oarepo_oidc_einfra/perun/dump.py
oarepo_oidc_einfra/perun/mapping.py
oarepo_oidc_einfra/perun/oidc.py
oarepo_oidc_einfra/services/__init__.py
oarepo_oidc_einfra/services/components/__init__.py
oarepo_oidc_einfra/services/components/aai_communities.py
oarepo_oidc_einfra/services/components/aai_invitations.py
oarepo_oidc_einfra/services/requests/__init__.py
oarepo_oidc_einfra/services/requests/invitation.py
oarepo_oidc_einfra/translations/messages.pot
oarepo_oidc_einfra/translations/cs/LC_MESSAGES/messages.mo
oarepo_oidc_einfra/translations/cs/LC_MESSAGES/messages.po
oarepo_oidc_einfra/translations/en/LC_MESSAGES/messages.mo
oarepo_oidc_einfra/translations/en/LC_MESSAGES/messages.po
oarepo_oidc_einfra_uvt_lter-1.0.5.dist-info/licenses/AUTHORS.rst
oarepo_oidc_einfra_uvt_lter-1.0.5.dist-info/licenses/LICENSE
oarepo_oidc_einfra_uvt_lter-1.0.5.dist-info/METADATA
oarepo_oidc_einfra_uvt_lter-1.0.5.dist-info/WHEEL
oarepo_oidc_einfra_uvt_lter-1.0.5.dist-info/entry_points.txt
oarepo_oidc_einfra_uvt_lter-1.0.5.dist-info/top_level.txt
oarepo_oidc_einfra_uvt_lter-1.0.5.dist-info/RECORD
